sdk/__init__.py
sdk/_internal_utils.py
sdk/api.py
sdk/config.py
sdk_api-0.2.1.dist-info/LICENSE
sdk_api-0.2.1.dist-info/METADATA
sdk_api-0.2.1.dist-info/WHEEL
sdk_api-0.2.1.dist-info/top_level.txt
sdk_api-0.2.1.dist-info/RECORD
