Metadata-Version: 2.1
Name: sdk-api
Version: 0.2.1
Summary: A Python API wrapping services of the Superb Data Kraken (SDK)
Author-email: "Team SDK | e:fs TechHub GmbH" <sdk@efs-techhub.com>
Maintainer: David Eichiner
Maintainer-email: david.eichiner@efs-techhub.com
License: Apache-2.0
Keywords: sdk,api,superb data kraken,data management,wrapper,api-wrapper
Classifier: Programming Language :: Python :: 3
Classifier: License :: OSI Approved :: Apache Software License
Classifier: Operating System :: OS Independent
Classifier: Development Status :: 3 - Alpha
Classifier: Intended Audience :: Developers
Requires-Python: >=3.7
License-File: LICENSE
Requires-Dist: elasticsearch (==7.13.1)
Requires-Dist: requests (>=2.28.2)
Requires-Dist: PyJWT (~=2.6.0)
Requires-Dist: azure-core (==1.16.0)
Requires-Dist: azure-storage-blob (==12.8.1)
Requires-Dist: msrest (==0.6.21)
